{
  "1766621545586": {
    "Title": "$SPON - (CM/WEATHER) STAR GRAINS YOKO RICE ",
    "StartTime": "2025-12-25 08:12:25",
    "Duration": "0:11"
  },
  "1766621557098": {
    "Title": "$SPON - INFO-ED - GOODAY - BEAUTY TIPS - THURSDAY",
    "StartTime": "2025-12-25 08:12:37",
    "Duration": "0:46"
  },
  "1766621602449": {
    "Title": "$SPON - NHB - TAMIL YOUTH FESTIVAL 2026",
    "StartTime": "2025-12-25 08:13:22",
    "Duration": "0:29"
  },
  "1766621632426": {
    "Title": "$SPON - PIZZAHUT - CHRISTMAS CHEESY BITES PERFORMANCE CAMPAIGN (PH 3- FESTIVE YEAR END ADVANCE ORDER)",
    "StartTime": "2025-12-25 08:13:52",
    "Duration": "0:34"
  },
  "1766621667143": {
    "Title": "$SPON 968ICA7 WOODLANDS CHECKPOINT HEAVY DEPARTURE TRAFFIC DUE TO TAILBACK FROM MALAYSIA",
    "StartTime": "2025-12-25 08:14:27",
    "Duration": "0:27"
  },
  "1766622636163": {
    "Title": "$SPON - (CM/TRAFFIC WATCH) SRI AMBIKAS - OOTY DHALL",
    "StartTime": "2025-12-25 08:30:36",
    "Duration": "0:12"
  },
  "1766622648527": {
    "Title": "$SPON - SPH MEDIA LTD - VASANTHAM TAMIZH PARTNERSHIP ",
    "StartTime": "2025-12-25 08:30:48",
    "Duration": "0:49"
  },
  "1766622698102": {
    "Title": "$SPON - JOTHI STORE - APAPA FACE WASH & SOAP",
    "StartTime": "2025-12-25 08:31:38",
    "Duration": "0:30"
  },
  "1766622743243": {
    "Title": "$SPON - (CM/8.30AM MEAL TIME CHECK) SYED - ANARKALI CLASSIC BASMATI RICE",
    "StartTime": "2025-12-25 08:32:23",
    "Duration": "0:16"
  },
  "1766623308979": {
    "Title": "$SPON - (CM/TRAFFIC WATCH) SRI AMBIKAS - OOTY DHALL",
    "StartTime": "2025-12-25 08:41:48",
    "Duration": "0:12"
  },
  "1766623321311": {
    "Title": "$SPON - SCDF - ELECTRICAL ",
    "StartTime": "2025-12-25 08:42:01",
    "Duration": "0:45"
  },
  "1766623366089": {
    "Title": "$SPON - GAYATRI - NAKULAN ",
    "StartTime": "2025-12-25 08:42:46",
    "Duration": "0:30"
  },
  "1766623395895": {
    "Title": "$SPON 968ICA7 WOODLANDS CHECKPOINT HEAVY DEPARTURE TRAFFIC DUE TO TAILBACK FROM MALAYSIA",
    "StartTime": "2025-12-25 08:43:15",
    "Duration": "0:27"
  },
  "1766623937187": {
    "Title": "$SPON - (CM/TRAFFIC WATCH) SRI AMBIKAS - OOTY DHALL",
    "StartTime": "2025-12-25 08:52:17",
    "Duration": "0:12"
  },
  "1766623949554": {
    "Title": "$SPON - VANTAGE AUTOMOTIVE - BYD (SCRIPT 1)",
    "StartTime": "2025-12-25 08:52:29",
    "Duration": "0:30"
  },
  "1766623979487": {
    "Title": "$SPON - MSR INTERIOR DESIGN (MEGA WEDDING EXPO)",
    "StartTime": "2025-12-25 08:52:59",
    "Duration": "0:30"
  },
  "1766624498955": {
    "Title": "$SPON - (CM/TRAFFIC WATCH) SRI AMBIKAS - OOTY DHALL",
    "StartTime": "2025-12-25 09:01:38",
    "Duration": "0:12"
  },
  "1766624511257": {
    "Title": "$SPON - JOYALUKKAS JEWELLERY BRANDING (SCRATCH & WIN CAMPAIGN)",
    "StartTime": "2025-12-25 09:01:51",
    "Duration": "0:30"
  },
  "1766624540989": {
    "Title": "$SPON - LEUNG KAI FOOK - AXE OIL (RAFI & VIMALA)",
    "StartTime": "2025-12-25 09:02:20",
    "Duration": "0:29"
  },
  "1766624600263": {
    "Title": "$SPON - (CM/WEATHER) STAR GRAINS YOKO RICE ",
    "StartTime": "2025-12-25 09:03:20",
    "Duration": "0:11"
  },
  "1766624611761": {
    "Title": "$SPON - CM - JOTHI STORE - STINGER- WEEKDAYS - EM BELT",
    "StartTime": "2025-12-25 09:03:31",
    "Duration": "0:14"
  },
  "1766624911966": {
    "Title": "$SPON - (CM/YOUTH'S CHOICE SONGS) ALKA JEWELLERS - GENERIC VER 2",
    "StartTime": "2025-12-25 09:08:31",
    "Duration": "0:17"
  },
  "1766624935069": {
    "Title": "$SPON - (CM/TRAFFIC WATCH) SRI AMBIKAS - OOTY DHALL",
    "StartTime": "2025-12-25 09:08:55",
    "Duration": "0:12"
  },
  "1766624947413": {
    "Title": "$SPON - PIZZAHUT - CHRISTMAS CHEESY BITES PERFORMANCE CAMPAIGN (PH 2B- MOLLY PWP WITH CHEESY BITES BUNDLE)",
    "StartTime": "2025-12-25 09:09:07",
    "Duration": "0:40"
  },
  "1766624987387": {
    "Title": "$SPON - VANTAGE AUTOMOTIVE - BYD (SCRIPT 1)",
    "StartTime": "2025-12-25 09:09:47",
    "Duration": "0:30"
  },
  "1766625017322": {
    "Title": "$SPON - NHB - TAMIL YOUTH FESTIVAL 2026",
    "StartTime": "2025-12-25 09:10:17",
    "Duration": "0:29"
  },
  "1766625047272": {
    "Title": "$SPON - TASTE OF INDIA - MIX ",
    "StartTime": "2025-12-25 09:10:47",
    "Duration": "0:30"
  },
  "1766625077219": {
    "Title": "$SPON 968ICA7 WOODLANDS CHECKPOINT HEAVY DEPARTURE TRAFFIC DUE TO TAILBACK FROM MALAYSIA",
    "StartTime": "2025-12-25 09:11:17",
    "Duration": "0:27"
  },
  "1766625154521": {
    "Title": "$SPON - INFO-ED - ANIMANI - ENTERTAINMENT - LEADOUT ",
    "StartTime": "2025-12-25 09:12:34",
    "Duration": "0:14"
  },
  "1766625703546": {
    "Title": "$SPON - (CM/ALL DAY HITS) SYED - ANARKALI CLASSIC BASMATI RICE",
    "StartTime": "2025-12-25 09:21:43",
    "Duration": "0:16"
  },
  "1766625725951": {
    "Title": "$SPON - (CM/TRAFFIC WATCH) SRI AMBIKAS - OOTY DHALL",
    "StartTime": "2025-12-25 09:22:05",
    "Duration": "0:12"
  },
  "1766625738301": {
    "Title": "$SPON - JOYALUKKAS JEWELLERY BRANDING (SCRATCH & WIN CAMPAIGN)",
    "StartTime": "2025-12-25 09:22:18",
    "Duration": "0:30"
  },
  "1766625768061": {
    "Title": "$SPON - COTHAS COFFEE",
    "StartTime": "2025-12-25 09:22:48",
    "Duration": "0:30"
  },
  "1766625798662": {
    "Title": "$SPON - PIZZAHUT - CHRISTMAS CHEESY BITES PERFORMANCE CAMPAIGN (PH 3- FESTIVE YEAR END ADVANCE ORDER)",
    "StartTime": "2025-12-25 09:23:18",
    "Duration": "0:34"
  },
  "1766625833454": {
    "Title": "$SPON - (PUB TRA) BYD VANTAGE AUTO 7AM-8AM SPONSOR ",
    "StartTime": "2025-12-25 09:23:53",
    "Duration": "0:45"
  },
  "1766625878117": {
    "Title": "$SPON - A2B SWEETS & VEG RESTAURANT VER 2 (SONG)",
    "StartTime": "2025-12-25 09:24:38",
    "Duration": "0:30"
  },
  "1766625908754": {
    "Title": "$SPON 968ICA7 WOODLANDS CHECKPOINT HEAVY DEPARTURE TRAFFIC DUE TO TAILBACK FROM MALAYSIA",
    "StartTime": "2025-12-25 09:25:08",
    "Duration": "0:27"
  },
  "1766625946042": {
    "Title": "$SPON - (CM/GOLD PRICE) DMY JEWELLERS - GOLD PRICE LEAD OUT",
    "StartTime": "2025-12-25 09:25:46",
    "Duration": "0:08"
  },
  "1766627990061": {
    "Title": "$SPON - CM - JOTHI STORE - CLOSING- WEEKDAYS - EM BELT",
    "StartTime": "2025-12-25 09:59:50",
    "Duration": "0:11"
  },
  "1766628779452": {
    "Title": "$SPON - (CM/JEWELLERY TRENDS TRIVIA) JOYALUKKAS JEWELLERY - THURSDAY V.",
    "StartTime": "2025-12-25 10:12:59",
    "Duration": "1:18"
  },
  "1766628906433": {
    "Title": "$SPON - (CM/MOTIVATIONAL QUOTES) SP MUTHIAH & SONS - GOLD PONNI RICE",
    "StartTime": "2025-12-25 10:15:06",
    "Duration": "0:12"
  },
  "1766629181539": {
    "Title": "$SPON - (CM/MEENDUM MEENDUM 70S & 80S) SP MUTHIAH & SONS - GOLD PONNI RICE",
    "StartTime": "2025-12-25 10:19:41",
    "Duration": "0:15"
  },
  "1766629196445": {
    "Title": "$SPON - VANTAGE AUTOMOTIVE - BYD (SCRIPT 1)",
    "StartTime": "2025-12-25 10:19:56",
    "Duration": "0:30"
  },
  "1766629226402": {
    "Title": "$SPON - A2B SWEETS & VEG RESTAURANT VER 2 (SONG)",
    "StartTime": "2025-12-25 10:20:26",
    "Duration": "0:30"
  },
  "1766629568489": {
    "Title": "$SPON 968ICA7 WOODLANDS CHECKPOINT HEAVY DEPARTURE TRAFFIC DUE TO TAILBACK FROM MALAYSIA",
    "StartTime": "2025-12-25 10:26:08",
    "Duration": "0:27"
  },
  "1766629676053": {
    "Title": "$SPON - INFO-ED - LKF HEALTH TIPS LEAD-OUT ",
    "StartTime": "2025-12-25 10:27:56",
    "Duration": "0:13"
  },
  "1766630247815": {
    "Title": "$SPON - (CM/ENDRO KETTA NYABAGAM 50S & 60S) SRI AMBIKAS - OOTY GOLD PONNI RICE",
    "StartTime": "2025-12-25 10:37:27",
    "Duration": "0:12"
  },
  "1766630260096": {
    "Title": "$SPON - JOTHI STORE - APAPA FACE WASH & SOAP",
    "StartTime": "2025-12-25 10:37:40",
    "Duration": "0:30"
  },
  "1766630290087": {
    "Title": "$SPON - TASTE OF INDIA - CAPTAIN PRABHAKARAN RE-RELEASE",
    "StartTime": "2025-12-25 10:38:10",
    "Duration": "0:30"
  },
  "1766630320082": {
    "Title": "$SPON 968ICA7 WOODLANDS CHECKPOINT HEAVY DEPARTURE TRAFFIC DUE TO TAILBACK FROM MALAYSIA",
    "StartTime": "2025-12-25 10:38:40",
    "Duration": "0:27"
  }
}